health/__init__.py
health/apps.py
health/consts.py
health/models.py
health/service.py
health/checkers/__init__.py
health/checkers/base.py
health/checkers/cache.py
health/checkers/database.py
health/checkers/disk.py
py_django_health-0.0.2.dist-info/LICENSE.txt
py_django_health-0.0.2.dist-info/METADATA
py_django_health-0.0.2.dist-info/WHEEL
py_django_health-0.0.2.dist-info/top_level.txt
py_django_health-0.0.2.dist-info/RECORD
